{
  "name": "GoWater Attendance Tracker (Production)",
  "nodes": [
    {
      "parameters": {
        "httpMethod": "POST",
        "path": "gowater-attendance",
        "responseMode": "responseNode",
        "options": {}
      },
      "id": "webhook-receiver",
      "name": "Webhook Receiver",
      "type": "n8n-nodes-base.webhook",
      "typeVersion": 2,
      "position": [200, 560],
      "webhookId": "gowater-attendance"
    },
    {
      "parameters": {
        "jsCode": "// ============================================================\n// HMAC-SHA256 Signature Verification\n// ============================================================\n// Ensures the webhook request actually came from GoWater\n// and wasn't spoofed by a third party.\n//\n// GoWater sends: X-Webhook-Signature: sha256=<hex>\n// We recompute the HMAC using our shared secret and compare.\n// ============================================================\n\nconst crypto = require('crypto');\n\nconst SHARED_SECRET = $env.GOWATER_WEBHOOK_SECRET || '';\n\nconst signature = $input.first().json.headers['x-webhook-signature'] || '';\nconst body = JSON.stringify($input.first().json.body);\n\nif (!SHARED_SECRET) {\n  // No secret configured — skip verification (dev mode)\n  return [{ json: { ...($input.first().json.body), _verified: false } }];\n}\n\nconst expected = 'sha256=' + crypto\n  .createHmac('sha256', SHARED_SECRET)\n  .update(body)\n  .digest('hex');\n\nif (signature !== expected) {\n  throw new Error('Invalid webhook signature — request rejected');\n}\n\nreturn [{ json: { ...($input.first().json.body), _verified: true } }];\n"
      },
      "id": "verify-signature",
      "name": "Verify HMAC Signature",
      "type": "n8n-nodes-base.code",
      "typeVersion": 2,
      "position": [420, 560],
      "notes": "Verifies HMAC-SHA256 signature from GoWater. Skips verification in dev mode (no secret configured). Throws error on invalid signature to halt the pipeline."
    },
    {
      "parameters": {
        "respondWith": "text",
        "responseBody": "OK",
        "options": {}
      },
      "id": "respond-ok",
      "name": "Respond OK",
      "type": "n8n-nodes-base.respondToWebhook",
      "typeVersion": 1,
      "position": [420, 400]
    },
    {
      "parameters": {
        "rules": {
          "values": [
            {
              "conditions": {
                "options": { "caseSensitive": true, "leftValue": "", "typeValidation": "strict" },
                "conditions": [
                  {
                    "leftValue": "={{ $json.event }}",
                    "rightValue": "attendance.checked_in",
                    "operator": { "type": "string", "operation": "equals" }
                  }
                ],
                "combinator": "and"
              },
              "renameOutput": true,
              "outputKey": "checked_in"
            },
            {
              "conditions": {
                "options": { "caseSensitive": true, "leftValue": "", "typeValidation": "strict" },
                "conditions": [
                  {
                    "leftValue": "={{ $json.event }}",
                    "rightValue": "attendance.checked_out",
                    "operator": { "type": "string", "operation": "equals" }
                  }
                ],
                "combinator": "and"
              },
              "renameOutput": true,
              "outputKey": "checked_out"
            },
            {
              "conditions": {
                "options": { "caseSensitive": true, "leftValue": "", "typeValidation": "strict" },
                "conditions": [
                  {
                    "leftValue": "={{ $json.event }}",
                    "rightValue": "attendance.break_started",
                    "operator": { "type": "string", "operation": "equals" }
                  }
                ],
                "combinator": "and"
              },
              "renameOutput": true,
              "outputKey": "break_started"
            },
            {
              "conditions": {
                "options": { "caseSensitive": true, "leftValue": "", "typeValidation": "strict" },
                "conditions": [
                  {
                    "leftValue": "={{ $json.event }}",
                    "rightValue": "attendance.break_ended",
                    "operator": { "type": "string", "operation": "equals" }
                  }
                ],
                "combinator": "and"
              },
              "renameOutput": true,
              "outputKey": "break_ended"
            }
          ]
        },
        "options": {
          "fallbackOutput": "extra"
        }
      },
      "id": "route-event",
      "name": "Route by Event",
      "type": "n8n-nodes-base.switch",
      "typeVersion": 3,
      "position": [860, 560]
    },
    {
      "parameters": {
        "jsCode": "// ============================================================\n// Late Check-In Detection (Philippines Labor Standards)\n// ============================================================\n// Standard shift starts at 9:00 AM PHT (UTC+8).\n// If check-in is after 9:00 AM, flag as late and calculate\n// how many minutes late.\n// ============================================================\n\nconst item = $input.first().json;\nconst ts = new Date(item.timestamp);\n\n// Convert to PHT (UTC+8) using manual offset\n// (toLocaleTimeString is unreliable on server runtimes)\nconst phtMs = ts.getTime() + (8 * 60 * 60 * 1000);\nconst pht = new Date(phtMs);\nconst hours = pht.getUTCHours();\nconst minutes = pht.getUTCMinutes();\n\n// 9:00 AM threshold\nconst SHIFT_START_HOUR = 9;\nconst SHIFT_START_MIN = 0;\n\nconst isLate = (hours > SHIFT_START_HOUR) ||\n  (hours === SHIFT_START_HOUR && minutes > SHIFT_START_MIN);\n\nlet minutesLate = 0;\nif (isLate) {\n  minutesLate = ((hours - SHIFT_START_HOUR) * 60) + (minutes - SHIFT_START_MIN);\n}\n\nconst timeStr = `${String(hours % 12 || 12).padStart(2, '0')}:${String(minutes).padStart(2, '0')} ${hours >= 12 ? 'PM' : 'AM'}`;\n\nreturn [{\n  json: {\n    ...item,\n    _phtTime: timeStr,\n    _isLate: isLate,\n    _minutesLate: minutesLate\n  }\n}];\n"
      },
      "id": "check-late",
      "name": "Check Late Arrival",
      "type": "n8n-nodes-base.code",
      "typeVersion": 2,
      "position": [1080, 340]
    },
    {
      "parameters": {
        "jsCode": "// ============================================================\n// Format Check-In Blocks (Slack Block Kit)\n// ============================================================\n// Builds a Block Kit JSON payload for the check-in message.\n// Includes: header, employee details, task list, and photo.\n// ============================================================\n\nconst item = $input.first().json;\nconst d = item.data;\nconst tasks = d.tasks || [];\n\n// Build task list text\nlet taskText = '*Planned Tasks:*\\n';\nif (tasks.length === 0) {\n  taskText += '_No tasks assigned_';\n} else {\n  tasks.forEach((t, i) => {\n    const statusLabel = (t.status || 'pending').replace(/_/g, ' ').replace(/\\b\\w/g, c => c.toUpperCase());\n    taskText += `${i + 1}. ${t.title} [${statusLabel}]\\n`;\n    const subs = t.subTasks || [];\n    subs.forEach(s => {\n      const subStatus = s.completed ? 'Done' : 'Pending';\n      taskText += `    - ${s.title} [${subStatus}]\\n`;\n    });\n  });\n}\n\n// Build info text\nlet infoText = `*Employee:* ${d.employeeName} (${d.employeeId})\\n`;\ninfoText += `*Date:* ${d.date}\\n`;\ninfoText += `*Location:* ${d.workLocation}\\n`;\ninfoText += `*Time:* ${item._phtTime}`;\nif (item._isLate) {\n  infoText += ` (${item._minutesLate} min late)`;\n}\nif (d.notes) {\n  infoText += `\\n*Notes:* ${d.notes}`;\n}\n\n// Build blocks array\nconst blocks = [\n  { type: 'header', text: { type: 'plain_text', text: 'Check In', emoji: false } },\n  { type: 'section', text: { type: 'mrkdwn', text: infoText } },\n  { type: 'section', text: { type: 'mrkdwn', text: taskText } }\n];\n\nif (d.photoUrl) {\n  blocks.push({ type: 'image', image_url: d.photoUrl, alt_text: 'Check-in photo' });\n}\n\nreturn [{ json: { ...item, _blocks: JSON.stringify(blocks) } }];\n"
      },
      "id": "format-checkin-blocks",
      "name": "Format Check-In Blocks",
      "type": "n8n-nodes-base.code",
      "typeVersion": 2,
      "position": [1520, 420]
    },
    {
      "parameters": {
        "channel": "#attendance",
        "text": "=Check In — {{ $json.data.employeeName }}",
        "otherOptions": {
          "includeLinkToWorkflow": false,
          "blocksUi": "={{ $json._blocks }}"
        }
      },
      "id": "slack-checkin",
      "name": "Slack: Check In",
      "type": "n8n-nodes-base.slack",
      "typeVersion": 2.2,
      "position": [1740, 420],
      "credentials": {
        "slackApi": {
          "id": "REPLACE_WITH_YOUR_SLACK_CREDENTIAL_ID",
          "name": "Slack Account"
        }
      }
    },
    {
      "parameters": {
        "jsCode": "// ============================================================\n// Check-Out: Calculate overtime & format hours\n// ============================================================\n// Philippine labor: regular = 8 hrs, OT = anything above 8.\n// OT rate: 1.25x on regular days.\n// Night differential: +10% for work between 10 PM - 6 AM.\n// ============================================================\n\nconst item = $input.first().json;\nconst totalHours = Number(item.data.totalHours) || 0;\nconst breakSec = Number(item.data.breakDuration) || 0;\nconst breakMins = Math.floor(breakSec / 60);\n\nconst REGULAR_HOURS = 8;\nconst netHours = totalHours;\nconst overtime = Math.max(0, netHours - REGULAR_HOURS);\nconst regularHrs = Math.min(netHours, REGULAR_HOURS);\nconst isUndertime = netHours < REGULAR_HOURS;\nconst undertimeHrs = isUndertime ? (REGULAR_HOURS - netHours) : 0;\n\n// Format check-out time to PHT\nconst ts = new Date(item.data.checkOutTime || item.timestamp);\nconst phtMs = ts.getTime() + (8 * 60 * 60 * 1000);\nconst pht = new Date(phtMs);\nconst hours = pht.getUTCHours();\nconst minutes = pht.getUTCMinutes();\nconst timeStr = `${String(hours % 12 || 12).padStart(2, '0')}:${String(minutes).padStart(2, '0')} ${hours >= 12 ? 'PM' : 'AM'}`;\n\nreturn [{\n  json: {\n    ...item,\n    _phtTime: timeStr,\n    _regularHrs: regularHrs.toFixed(2),\n    _overtimeHrs: overtime.toFixed(2),\n    _netHours: netHours.toFixed(2),\n    _isUndertime: isUndertime,\n    _undertimeHrs: undertimeHrs.toFixed(2),\n    _hasOvertime: overtime > 0,\n    _breakMins: breakMins\n  }\n}];\n"
      },
      "id": "calc-checkout",
      "name": "Calculate Hours & OT",
      "type": "n8n-nodes-base.code",
      "typeVersion": 2,
      "position": [1080, 560]
    },
    {
      "parameters": {
        "jsCode": "// ============================================================\n// Format Check-Out Blocks (Slack Block Kit)\n// ============================================================\n// Builds a Block Kit JSON payload for the check-out message.\n// Includes: header, hours summary, task updates, and photo.\n// ============================================================\n\nconst item = $input.first().json;\nconst d = item.data;\nconst tasks = d.tasks || [];\n\n// Build task list text\nlet taskText = '*Task Updates:*\\n';\nif (tasks.length === 0) {\n  taskText += '_No tasks assigned_';\n} else {\n  tasks.forEach((t, i) => {\n    const statusLabel = (t.status || 'pending').replace(/_/g, ' ').replace(/\\b\\w/g, c => c.toUpperCase());\n    taskText += `${i + 1}. ${t.title} [${statusLabel}]\\n`;\n    const subs = t.subTasks || [];\n    subs.forEach(s => {\n      const subStatus = s.completed ? 'Done' : 'Pending';\n      taskText += `    - ${s.title} [${subStatus}]\\n`;\n    });\n  });\n}\n\n// Build info text\nlet infoText = `*Employee:* ${d.employeeName} (${d.employeeId})\\n`;\ninfoText += `*Date:* ${d.date}\\n`;\ninfoText += `*Check Out:* ${item._phtTime}\\n`;\ninfoText += `*Net Hours:* ${item._netHours}h | Regular: ${item._regularHrs}h`;\nif (item._hasOvertime) {\n  infoText += ` | OT: ${item._overtimeHrs}h`;\n}\nif (item._isUndertime) {\n  infoText += `\\n*Undertime:* ${item._undertimeHrs}h`;\n}\ninfoText += `\\n*Break:* ${item._breakMins} min`;\n\n// Build blocks array\nconst blocks = [\n  { type: 'header', text: { type: 'plain_text', text: 'Check Out', emoji: false } },\n  { type: 'section', text: { type: 'mrkdwn', text: infoText } },\n  { type: 'section', text: { type: 'mrkdwn', text: taskText } }\n];\n\nif (d.photoUrl) {\n  blocks.push({ type: 'image', image_url: d.photoUrl, alt_text: 'Check-out photo' });\n}\n\nreturn [{ json: { ...item, _blocks: JSON.stringify(blocks) } }];\n"
      },
      "id": "format-checkout-blocks",
      "name": "Format Check-Out Blocks",
      "type": "n8n-nodes-base.code",
      "typeVersion": 2,
      "position": [1300, 560]
    },
    {
      "parameters": {
        "channel": "#attendance",
        "text": "=Check Out — {{ $json.data.employeeName }}",
        "otherOptions": {
          "includeLinkToWorkflow": false,
          "blocksUi": "={{ $json._blocks }}"
        }
      },
      "id": "slack-checkout",
      "name": "Slack: Check Out",
      "type": "n8n-nodes-base.slack",
      "typeVersion": 2.2,
      "position": [1520, 560],
      "credentials": {
        "slackApi": {
          "id": "REPLACE_WITH_YOUR_SLACK_CREDENTIAL_ID",
          "name": "Slack Account"
        }
      }
    },
    {
      "parameters": {
        "channel": "#attendance",
        "text": "=*Break Started*\n\n*Employee:* {{ $json.data.employeeName }} ({{ $json.data.employeeId }})\n*Date:* {{ $json.data.date }}\n*Break Start:* {{ new Date(new Date($json.data.breakStartTime || $json.timestamp).getTime() + (8*60*60*1000)).toISOString().substring(11,16) }} PHT",
        "otherOptions": {
          "includeLinkToWorkflow": false
        }
      },
      "id": "slack-break-start",
      "name": "Slack: Break Start",
      "type": "n8n-nodes-base.slack",
      "typeVersion": 2.2,
      "position": [1080, 740],
      "credentials": {
        "slackApi": {
          "id": "REPLACE_WITH_YOUR_SLACK_CREDENTIAL_ID",
          "name": "Slack Account"
        }
      }
    },
    {
      "parameters": {
        "jsCode": "// ============================================================\n// Break Compliance: Philippine DOLE Labor Standards\n// ============================================================\n// DOLE Rule: Employees working 6+ hours are entitled to a\n// 60-minute meal break (not counted as work time).\n// Breaks shorter than 20 minutes are counted as work time.\n//\n// This node checks:\n// 1. Break too short (< 30 min) — may violate DOLE standards\n// 2. Break too long  (> 120 min) — needs manager review\n// ============================================================\n\nconst item = $input.first().json;\nconst breakSec = Number(item.data.breakDurationSeconds) || 0;\nconst breakMin = Math.floor(breakSec / 60);\nconst totalBreakMin = Math.floor((Number(item.data.totalBreakDuration) || 0) / 60);\n\nconst SHORT_BREAK_THRESHOLD = 30;  // minutes\nconst LONG_BREAK_THRESHOLD = 120;  // minutes\n\nlet complianceFlag = 'ok';\nlet complianceMsg = '';\n\nif (breakMin < SHORT_BREAK_THRESHOLD) {\n  complianceFlag = 'short_break';\n  complianceMsg = `Break was only ${breakMin} min — possible DOLE compliance issue (minimum 60 min for 6+ hr shifts)`;\n} else if (breakMin > LONG_BREAK_THRESHOLD) {\n  complianceFlag = 'long_break';\n  complianceMsg = `Extended break of ${breakMin} min — needs manager review`;\n}\n\nreturn [{\n  json: {\n    ...item,\n    _breakMin: breakMin,\n    _totalBreakMin: totalBreakMin,\n    _complianceFlag: complianceFlag,\n    _complianceMsg: complianceMsg\n  }\n}];\n"
      },
      "id": "check-break-compliance",
      "name": "Check Break Compliance",
      "type": "n8n-nodes-base.code",
      "typeVersion": 2,
      "position": [1080, 920]
    },
    {
      "parameters": {
        "conditions": {
          "options": { "caseSensitive": true, "leftValue": "", "typeValidation": "strict" },
          "conditions": [
            {
              "leftValue": "={{ $json._complianceFlag }}",
              "rightValue": "ok",
              "operator": { "type": "string", "operation": "notEquals" }
            }
          ],
          "combinator": "and"
        },
        "options": {}
      },
      "id": "has-compliance-issue",
      "name": "Compliance Issue?",
      "type": "n8n-nodes-base.if",
      "typeVersion": 2,
      "position": [1300, 920]
    },
    {
      "parameters": {
        "channel": "#attendance",
        "text": "=*Break Compliance Alert*\n\n*Employee:* {{ $json.data.employeeName }} ({{ $json.data.employeeId }})\n*Date:* {{ $json.data.date }}\n*Break Duration:* {{ $json._breakMin }} min\n*Issue:* {{ $json._complianceMsg }}\n*Total Break Today:* {{ $json._totalBreakMin }} min",
        "otherOptions": {
          "includeLinkToWorkflow": false
        }
      },
      "id": "slack-compliance-alert",
      "name": "Slack: Compliance Alert",
      "type": "n8n-nodes-base.slack",
      "typeVersion": 2.2,
      "position": [1520, 860],
      "credentials": {
        "slackApi": {
          "id": "REPLACE_WITH_YOUR_SLACK_CREDENTIAL_ID",
          "name": "Slack Account"
        }
      }
    },
    {
      "parameters": {
        "channel": "#attendance",
        "text": "=*Break Ended*\n\n*Employee:* {{ $json.data.employeeName }} ({{ $json.data.employeeId }})\n*Date:* {{ $json.data.date }}\n*Break Duration:* {{ $json._breakMin }} min\n*Total Break Today:* {{ $json._totalBreakMin }} min{{ $json._complianceFlag !== 'ok' ? '\\n' + $json._complianceMsg : '' }}",
        "otherOptions": {
          "includeLinkToWorkflow": false
        }
      },
      "id": "slack-break-end",
      "name": "Slack: Break End",
      "type": "n8n-nodes-base.slack",
      "typeVersion": 2.2,
      "position": [1520, 980],
      "credentials": {
        "slackApi": {
          "id": "REPLACE_WITH_YOUR_SLACK_CREDENTIAL_ID",
          "name": "Slack Account"
        }
      }
    },
    {
      "parameters": {
        "operation": "appendOrUpdate",
        "documentId": { "__rl": true, "mode": "url", "value": "REPLACE_WITH_YOUR_GOOGLE_SHEET_URL" },
        "sheetName": { "__rl": true, "mode": "name", "value": "Attendance Log" },
        "columns": {
          "mappingMode": "defineBelow",
          "value": {
            "date": "={{ $json.data.date }}",
            "employee_id": "={{ $json.data.employeeId }}",
            "employee_name": "={{ $json.data.employeeName }}",
            "event": "={{ $json.event }}",
            "time": "={{ $json.timestamp }}",
            "location": "={{ $json.data.workLocation || '' }}",
            "total_hours": "={{ $json.data.totalHours || '' }}",
            "break_minutes": "={{ $json._breakMin || $json._totalBreakMin || '' }}",
            "overtime_hours": "={{ $json._overtimeHrs || '' }}",
            "flags": "={{ $json._isLate ? 'LATE(' + $json._minutesLate + 'min)' : '' }}{{ $json._complianceFlag && $json._complianceFlag !== 'ok' ? ' BREAK_ISSUE' : '' }}{{ $json._isUndertime ? ' UNDERTIME(' + $json._undertimeHrs + 'h)' : '' }}"
          }
        },
        "options": {}
      },
      "id": "gsheets-log",
      "name": "Google Sheets: Audit Log",
      "type": "n8n-nodes-base.googleSheets",
      "typeVersion": 4.5,
      "position": [860, 780],
      "credentials": {
        "googleSheetsOAuth2Api": {
          "id": "REPLACE_WITH_YOUR_GOOGLE_CREDENTIAL_ID",
          "name": "Google Sheets Account"
        }
      }
    },
    {
      "parameters": {
        "rule": {
          "interval": [
            {
              "triggerAtHour": 18,
              "triggerAtMinute": 0
            }
          ]
        }
      },
      "id": "daily-cron",
      "name": "Daily 6 PM PHT",
      "type": "n8n-nodes-base.scheduleTrigger",
      "typeVersion": 1.2,
      "position": [200, 1200]
    },
    {
      "parameters": {
        "url": "={{ $env.GOWATER_API_URL }}/api/attendance/daily-summary",
        "authentication": "none",
        "sendHeaders": true,
        "headerParameters": {
          "parameters": [
            {
              "name": "X-API-Key",
              "value": "={{ $env.GOWATER_API_KEY }}"
            }
          ]
        },
        "options": {
          "timeout": 10000
        }
      },
      "id": "fetch-daily-summary",
      "name": "Fetch Daily Summary",
      "type": "n8n-nodes-base.httpRequest",
      "typeVersion": 4.2,
      "position": [420, 1200]
    },
    {
      "parameters": {
        "jsCode": "// ============================================================\n// Daily Summary Report Builder\n// ============================================================\n// Aggregates the day's attendance data into a formatted Slack\n// message with key metrics, flags, and employee status.\n// Outputs TWO items:\n//   [0] = full daily report for #attendance\n//   [1] = absent employee list for #absent\n// ============================================================\n\nconst data = $input.first().json;\nconst employees = data.employees || [];\nconst date = data.date || new Date().toISOString().split('T')[0];\n\nconst total = employees.length;\nconst checkedIn = employees.filter(e => e.checked_in).length;\nconst checkedOut = employees.filter(e => e.checked_out).length;\nconst stillWorking = employees.filter(e => e.checked_in && !e.checked_out).length;\nconst onBreak = employees.filter(e => e.on_break).length;\nconst absent = employees.filter(e => !e.checked_in).length;\nconst lateArrivals = employees.filter(e => e.is_late);\nconst overtimeWorkers = employees.filter(e => Number(e.overtime_hours) > 0);\nconst undertimeWorkers = employees.filter(e => e.checked_out && Number(e.net_hours) < 8);\nconst breakViolations = employees.filter(e => e.break_violation);\n\nlet report = `*Daily Attendance Report — ${date}*\\n`;\nreport += `━━━━━━━━━━━━━━━━━━━━━━━━━━━━\\n\\n`;\n\n// Status overview\nreport += `*Team Status*\\n`;\nreport += `Total: ${total} | Checked In: ${checkedIn} | Checked Out: ${checkedOut}\\n`;\nreport += `Still Working: ${stillWorking} | On Break: ${onBreak} | Absent: ${absent}\\n\\n`;\n\n// Late arrivals\nif (lateArrivals.length > 0) {\n  report += `*Late Arrivals (${lateArrivals.length})*\\n`;\n  lateArrivals.forEach(e => {\n    report += `  - ${e.name}: ${e.minutes_late} min late\\n`;\n  });\n  report += `\\n`;\n}\n\n// Overtime\nif (overtimeWorkers.length > 0) {\n  report += `*Overtime (${overtimeWorkers.length})*\\n`;\n  overtimeWorkers.forEach(e => {\n    report += `  - ${e.name}: +${Number(e.overtime_hours).toFixed(1)}h OT\\n`;\n  });\n  report += `\\n`;\n}\n\n// Undertime\nif (undertimeWorkers.length > 0) {\n  report += `*Undertime (${undertimeWorkers.length})*\\n`;\n  undertimeWorkers.forEach(e => {\n    report += `  - ${e.name}: ${Number(e.net_hours).toFixed(1)}h (${(8 - Number(e.net_hours)).toFixed(1)}h short)\\n`;\n  });\n  report += `\\n`;\n}\n\n// Break violations\nif (breakViolations.length > 0) {\n  report += `*Break Compliance Issues (${breakViolations.length})*\\n`;\n  breakViolations.forEach(e => {\n    report += `  - ${e.name}: ${e.break_issue}\\n`;\n  });\n  report += `\\n`;\n}\n\n// Absent employees in daily report\nif (absent > 0) {\n  const absentList = employees.filter(e => !e.checked_in);\n  report += `*Absent (${absent})*\\n`;\n  absentList.forEach(e => {\n    report += `  - ${e.name}${e.on_leave ? ' (on leave)' : ''}\\n`;\n  });\n}\n\n// Build absent list for #absent channel\nconst absentEmployees = employees.filter(e => !e.checked_in);\nlet absentReport = `*Absent Employees — ${date}*\\n`;\nabsentReport += `━━━━━━━━━━━━━━━━━━━━━━━━━━━━\\n\\n`;\nif (absentEmployees.length === 0) {\n  absentReport += `All employees checked in today.`;\n} else {\n  absentReport += `*${absentEmployees.length} employee(s) did not check in:*\\n\\n`;\n  absentEmployees.forEach((e, i) => {\n    absentReport += `${i + 1}. ${e.name}${e.on_leave ? ' (on leave)' : ''}\\n`;\n  });\n}\n\nreturn [\n  { json: { report, date, _outputType: 'daily_report' } },\n  { json: { report: absentReport, date, _outputType: 'absent_list' } }\n];\n"
      },
      "id": "build-daily-report",
      "name": "Build Daily Report",
      "type": "n8n-nodes-base.code",
      "typeVersion": 2,
      "position": [640, 1200]
    },
    {
      "parameters": {
        "rules": {
          "values": [
            {
              "conditions": {
                "options": { "caseSensitive": true, "leftValue": "", "typeValidation": "strict" },
                "conditions": [
                  {
                    "leftValue": "={{ $json._outputType }}",
                    "rightValue": "daily_report",
                    "operator": { "type": "string", "operation": "equals" }
                  }
                ],
                "combinator": "and"
              },
              "renameOutput": true,
              "outputKey": "daily_report"
            },
            {
              "conditions": {
                "options": { "caseSensitive": true, "leftValue": "", "typeValidation": "strict" },
                "conditions": [
                  {
                    "leftValue": "={{ $json._outputType }}",
                    "rightValue": "absent_list",
                    "operator": { "type": "string", "operation": "equals" }
                  }
                ],
                "combinator": "and"
              },
              "renameOutput": true,
              "outputKey": "absent_list"
            }
          ]
        },
        "options": {
          "fallbackOutput": "extra"
        }
      },
      "id": "route-daily-output",
      "name": "Route Daily Output",
      "type": "n8n-nodes-base.switch",
      "typeVersion": 3,
      "position": [860, 1200]
    },
    {
      "parameters": {
        "channel": "#attendance",
        "text": "={{ $json.report }}",
        "otherOptions": {
          "includeLinkToWorkflow": false
        }
      },
      "id": "slack-daily-summary",
      "name": "Slack: Daily Summary",
      "type": "n8n-nodes-base.slack",
      "typeVersion": 2.2,
      "position": [1080, 1100],
      "credentials": {
        "slackApi": {
          "id": "REPLACE_WITH_YOUR_SLACK_CREDENTIAL_ID",
          "name": "Slack Account"
        }
      }
    },
    {
      "parameters": {
        "channel": "#absent",
        "text": "={{ $json.report }}",
        "otherOptions": {
          "includeLinkToWorkflow": false
        }
      },
      "id": "slack-absent-list",
      "name": "Slack: Absent List",
      "type": "n8n-nodes-base.slack",
      "typeVersion": 2.2,
      "position": [1080, 1300],
      "credentials": {
        "slackApi": {
          "id": "REPLACE_WITH_YOUR_SLACK_CREDENTIAL_ID",
          "name": "Slack Account"
        }
      }
    },
    {
      "parameters": {
        "operation": "appendOrUpdate",
        "documentId": { "__rl": true, "mode": "url", "value": "REPLACE_WITH_YOUR_GOOGLE_SHEET_URL" },
        "sheetName": { "__rl": true, "mode": "name", "value": "Daily Summaries" },
        "columns": {
          "mappingMode": "defineBelow",
          "value": {
            "date": "={{ $json.date }}",
            "report": "={{ $json.report }}"
          }
        },
        "options": {}
      },
      "id": "gsheets-daily-summary",
      "name": "Google Sheets: Daily Summary",
      "type": "n8n-nodes-base.googleSheets",
      "typeVersion": 4.5,
      "position": [1080, 1480],
      "credentials": {
        "googleSheetsOAuth2Api": {
          "id": "REPLACE_WITH_YOUR_GOOGLE_CREDENTIAL_ID",
          "name": "Google Sheets Account"
        }
      }
    },
    {
      "parameters": {
        "conditions": {
          "options": { "caseSensitive": true, "leftValue": "", "typeValidation": "strict" },
          "conditions": [
            {
              "leftValue": "={{ $json.event }}",
              "rightValue": "attendance.",
              "operator": { "type": "string", "operation": "startsWith" }
            }
          ],
          "combinator": "and"
        },
        "options": {}
      },
      "id": "is-valid-event",
      "name": "Valid Attendance Event?",
      "type": "n8n-nodes-base.if",
      "typeVersion": 2,
      "position": [640, 560],
      "notes": "Rejects non-attendance events early to prevent unexpected data in the pipeline"
    }
  ],
  "connections": {
    "Webhook Receiver": {
      "main": [
        [
          { "node": "Respond OK", "type": "main", "index": 0 },
          { "node": "Verify HMAC Signature", "type": "main", "index": 0 }
        ]
      ]
    },
    "Verify HMAC Signature": {
      "main": [
        [
          { "node": "Valid Attendance Event?", "type": "main", "index": 0 }
        ]
      ]
    },
    "Valid Attendance Event?": {
      "main": [
        [
          { "node": "Route by Event", "type": "main", "index": 0 },
          { "node": "Google Sheets: Audit Log", "type": "main", "index": 0 }
        ],
        []
      ]
    },
    "Route by Event": {
      "main": [
        [
          { "node": "Check Late Arrival", "type": "main", "index": 0 }
        ],
        [
          { "node": "Calculate Hours & OT", "type": "main", "index": 0 }
        ],
        [
          { "node": "Slack: Break Start", "type": "main", "index": 0 }
        ],
        [
          { "node": "Check Break Compliance", "type": "main", "index": 0 }
        ]
      ]
    },
    "Check Late Arrival": {
      "main": [
        [
          { "node": "Format Check-In Blocks", "type": "main", "index": 0 }
        ]
      ]
    },
    "Format Check-In Blocks": {
      "main": [
        [
          { "node": "Slack: Check In", "type": "main", "index": 0 }
        ]
      ]
    },
    "Calculate Hours & OT": {
      "main": [
        [
          { "node": "Format Check-Out Blocks", "type": "main", "index": 0 }
        ]
      ]
    },
    "Format Check-Out Blocks": {
      "main": [
        [
          { "node": "Slack: Check Out", "type": "main", "index": 0 }
        ]
      ]
    },
    "Check Break Compliance": {
      "main": [
        [
          { "node": "Compliance Issue?", "type": "main", "index": 0 },
          { "node": "Slack: Break End", "type": "main", "index": 0 }
        ]
      ]
    },
    "Compliance Issue?": {
      "main": [
        [
          { "node": "Slack: Compliance Alert", "type": "main", "index": 0 }
        ],
        []
      ]
    },
    "Daily 6 PM PHT": {
      "main": [
        [
          { "node": "Fetch Daily Summary", "type": "main", "index": 0 }
        ]
      ]
    },
    "Fetch Daily Summary": {
      "main": [
        [
          { "node": "Build Daily Report", "type": "main", "index": 0 }
        ]
      ]
    },
    "Build Daily Report": {
      "main": [
        [
          { "node": "Route Daily Output", "type": "main", "index": 0 }
        ]
      ]
    },
    "Route Daily Output": {
      "main": [
        [
          { "node": "Slack: Daily Summary", "type": "main", "index": 0 },
          { "node": "Google Sheets: Daily Summary", "type": "main", "index": 0 }
        ],
        [
          { "node": "Slack: Absent List", "type": "main", "index": 0 }
        ]
      ]
    }
  },
  "settings": {
    "executionOrder": "v1",
    "errorWorkflow": "REPLACE_WITH_ERROR_WORKFLOW_ID"
  },
  "pinData": {},
  "meta": {
    "templateCredsSetupCompleted": false,
    "instanceId": "gowater-hr-portal"
  },
  "tags": [
    { "name": "GoWater" },
    { "name": "Attendance" },
    { "name": "Slack" },
    { "name": "Compliance" },
    { "name": "Production" }
  ]
}
